{
    "siteGroups": [
        "Hauptseite"
    ],
    "sites": [
        {
            "group": "Hauptseite",
            "name": "Hauptseite",
            "handle": "default",
            "language": "de-DE",
            "primary": true,
            "hasUrls": true,
            "baseUrl": "$DEFAULT_SITE_URL"
        }
    ],
    "fieldGroups": [
        "Common"
    ],
    "sections": [
        {
            "name": "Seiten",
            "handle": "pages",
            "type": "structure",
            "enableVersioning": true,
            "maxLevels": "2",
            "siteSettings": [
                {
                    "hasUrls": true,
                    "uriFormat": "{% if object.level == 1 %}{slug}{% else %}{parent.uri}\/{slug}{% endif %}",
                    "template": "pages\/_entry",
                    "enabledByDefault": true
                }
            ]
        },
        {
            "name": "Startseite",
            "handle": "startseite",
            "type": "single",
            "enableVersioning": true,
            "siteSettings": [
                {
                    "hasUrls": true,
                    "uriFormat": "__home__",
                    "template": "index",
                    "enabledByDefault": true
                }
            ]
        }
    ],
    "fields": [
        {
            "group": "Common",
            "name": "Anlesetext",
            "handle": "anlesetext",
            "instructions": "",
            "type": "verbb\\vizy\\fields\\VizyField",
            "fieldData": [],
            "vizyConfig": "",
            "configSelectionMode": "manual",
            "manualConfig": "{\r\n    \"buttons\": [\"italic\", \"bold\"]\r\n}\r\n",
            "availableVolumes": "*",
            "availableTransforms": "*",
            "showUnpermittedVolumes": false,
            "showUnpermittedFiles": false,
            "defaultTransform": "",
            "columnType": "text"
        },
        {
            "group": "Common",
            "name": "Topline",
            "handle": "topline",
            "instructions": "",
            "type": "craft\\fields\\PlainText",
            "uiMode": "normal",
            "code": "",
            "multiline": "",
            "initialRows": "4"
        },
        {
            "group": "Common",
            "name": "\u00dcberschrift",
            "handle": "ueberschrift",
            "instructions": "",
            "type": "craft\\fields\\PlainText",
            "uiMode": "normal",
            "code": "",
            "multiline": "",
            "initialRows": "4"
        }
    ],
    "entryTypes": [
        {
            "sectionHandle": "pages",
            "name": "Standardseite",
            "handle": "default",
            "hasTitleField": true,
            "titleFormat": "",
            "fieldLayout": {
                "Inhalt": [
                    "__ui_1",
                    "body"
                ]
            },
            "fieldConfigs": {
                "Inhalt": {
                    "__ui_1": {
                        "type": "craft\\fieldlayoutelements\\EntryTitleField",
                        "width": 100
                    },
                    "body": {
                        "width": 100
                    }
                }
            }
        },
        {
            "sectionHandle": "startseite",
            "name": "Startseite",
            "handle": "startseite",
            "hasTitleField": true,
            "titleFormat": "",
            "fieldLayout": {
                "Inhalt": [
                    "__ui_1"
                ]
            },
            "fieldConfigs": {
                "Inhalt": {
                    "__ui_1": {
                        "type": "craft\\fieldlayoutelements\\EntryTitleField",
                        "width": 100
                    }
                }
            }
        }
    ]
}